{
  "name": "gtd-lite",
  "description": "Task-focused. GTD system + daily planning.",
  "agents": [
    "code-reviewer",
    "test-writer",
    "explorer",
    "architect",
    "refactorer",
    "pr-reviewer",
    "implementer",
    "parallel-worker"
  ],
  "commands": [
    "fix-issue",
    "review",
    "test",
    "plan",
    "research",
    "learn",
    "assumptions",
    "remember",
    "refactor",
    "gtd-capture",
    "gtd-process",
    "daily-plan",
    "worktree"
  ],
  "hooks": [
    "format",
    "lint",
    "typecheck",
    "block-rm-rf",
    "block-env",
    "block-main",
    "session-context",
    "stop-validator",
    "memory-precompact",
    "push-review"
  ],
  "features": {
    "memory": true,
    "spec_workflow": false,
    "gtd": true,
    "worktrees": true
  },
  "permission_mode": "permissive"
}
